gt911.py
circuitpython_gt911-0.2.1.dist-info/LICENSE
circuitpython_gt911-0.2.1.dist-info/METADATA
circuitpython_gt911-0.2.1.dist-info/WHEEL
circuitpython_gt911-0.2.1.dist-info/top_level.txt
circuitpython_gt911-0.2.1.dist-info/RECORD
