Metadata-Version: 2.1
Name: circuitpython-gt911
Version: 0.2.1
Summary: CircuitPython Driver for Goodix GT911-based touch screens
Author-email: Robert Grizzell <robert@grizzell.me>
License: MIT
Project-URL: Homepage, https://github.com/rgrizzell/CircuitPython_GT911
Keywords: adafruit,blinka,circuitpython,micropython,goodix,gt911,touch,touchscreen
Classifier: Intended Audience :: Developers
Classifier: Topic :: Software Development :: Libraries
Classifier: Topic :: Software Development :: Embedded Systems
Classifier: Topic :: System :: Hardware
Classifier: License :: OSI Approved :: MIT License
Classifier: Programming Language :: Python :: 3
License-File: LICENSE
Requires-Dist: Adafruit-Blinka
Requires-Dist: adafruit-circuitpython-busdevice
Requires-Dist: adafruit-circuitpython-register
Provides-Extra: optional
